allauth_xui/__init__.py
allauth_xui/apps.py
allauth_xui/mixins.py
allauth_xui/static/allauth_xui/.prettierrc
allauth_xui/static/allauth_xui/README.md
allauth_xui/static/allauth_xui/css/app.css
allauth_xui/static/allauth_xui/css/styles.css
allauth_xui/static/allauth_xui/package-lock.json
allauth_xui/static/allauth_xui/package.json
allauth_xui/templates/account/account_inactive.html
allauth_xui/templates/account/base_confirm_code.html
allauth_xui/templates/account/base_entrance.html
allauth_xui/templates/account/base_manage.html
allauth_xui/templates/account/base_manage_email.html
allauth_xui/templates/account/base_manage_password.html
allauth_xui/templates/account/base_manage_phone.html
allauth_xui/templates/account/base_reauthenticate.html
allauth_xui/templates/account/confirm_email_verification_code.html
allauth_xui/templates/account/confirm_login_code.html
allauth_xui/templates/account/confirm_password_reset_code.html
allauth_xui/templates/account/confirm_phone_verification_code.html
allauth_xui/templates/account/email.html
allauth_xui/templates/account/email_change.html
allauth_xui/templates/account/email_confirm.html
allauth_xui/templates/account/login.html
allauth_xui/templates/account/logout.html
allauth_xui/templates/account/password_change.html
allauth_xui/templates/account/password_reset.html
allauth_xui/templates/account/password_reset_done.html
allauth_xui/templates/account/password_reset_from_key.html
allauth_xui/templates/account/password_reset_from_key_done.html
allauth_xui/templates/account/password_set.html
allauth_xui/templates/account/phone_change.html
allauth_xui/templates/account/reauthenticate.html
allauth_xui/templates/account/request_login_code.html
allauth_xui/templates/account/signup.html
allauth_xui/templates/account/signup_by_passkey.html
allauth_xui/templates/account/signup_closed.html
allauth_xui/templates/account/snippets/already_logged_in.html
allauth_xui/templates/account/snippets/warn_no_email.html
django_allauth_xui-0.1.1.dist-info/METADATA
django_allauth_xui-0.1.1.dist-info/WHEEL
django_allauth_xui-0.1.1.dist-info/licenses/LICENSE
django_allauth_xui-0.1.1.dist-info/RECORD
