Metadata-Version: 2.4
Name: django-allauth-xui
Version: 0.1.1
Summary: Modern, responsive UI layer for django-allauth, styled with TailwindCSS and daisyUI.
License: MIT
License-File: LICENSE
Author: Yousef Abu Shanab
Author-email: josephyousef249@gmail.com
Requires-Python: >=3.11
Classifier: License :: OSI Approved :: MIT License
Classifier: Programming Language :: Python :: 3
Classifier: Programming Language :: Python :: 3.11
Classifier: Programming Language :: Python :: 3.12
Classifier: Programming Language :: Python :: 3.13
Classifier: Programming Language :: Python :: 3.14
Requires-Dist: django (>=5.2.7)
Requires-Dist: django-allauth (>=65.13.0)
Project-URL: Documentation, https://github.com/youzarsiph/django-allauth-xui
Project-URL: Homepage, https://github.com/youzarsiph/django-allauth-xui
Project-URL: Repository, https://github.com/youzarsiph/django-allauth-xui
